[
  {
    "id": "71b3ca14-425d-4cc6-a662-c7222ec6b0a9",
    "date": "2026-06-30T05:15:03.248Z",
    "timestamp": "2026-06-30T05:15:03.248000",
    "level": "success",
    "status": "00000",
    "method": "",
    "pathname": "",
    "event_message": "connection authenticated: identity=\"postgres\" method=scram-sha-256 (/etc/postgresql/pg_hba.conf:97)",
    "headers": {},
    "regions": [],
    "log_type": "postgres",
    "latency": 0,
    "log_count": null,
    "logs": [],
    "auth_user": null
  },
  {
    "id": "6367d80c-156a-4f77-91f3-1d85e1c1176f",
    "date": "2026-06-30T05:15:03.173Z",
    "timestamp": "2026-06-30T05:15:03.173000",
    "level": "success",
    "status": "00000",
    "method": "",
    "pathname": "",
    "event_message": "connection authenticated: identity=\"postgres\" method=scram-sha-256 (/etc/postgresql/pg_hba.conf:97)",
    "headers": {},
    "regions": [],
    "log_type": "postgres",
    "latency": 0,
    "log_count": null,
    "logs": [],
    "auth_user": null
  },
  {
    "id": "33215973-bfbe-40c4-806e-53ef64e4a01f",
    "date": "2026-06-30T05:15:03.097Z",
    "timestamp": "2026-06-30T05:15:03.097000",
    "level": "success",
    "status": "00000",
    "method": "",
    "pathname": "",
    "event_message": "connection authenticated: identity=\"postgres\" method=scram-sha-256 (/etc/postgresql/pg_hba.conf:97)",
    "headers": {},
    "regions": [],
    "log_type": "postgres",
    "latency": 0,
    "log_count": null,
    "logs": [],
    "auth_user": null
  },
  {
    "id": "f59d7674-18de-46b2-ab10-fcf92bdfd5e3",
    "date": "2026-06-30T05:15:02.898Z",
    "timestamp": "2026-06-30T05:15:02.898000",
    "level": "success",
    "status": "00000",
    "method": "",
    "pathname": "",
    "event_message": "connection received: host=2406:da18:96a:8200:c712:656d:fab9:f6f6 port=33432",
    "headers": {},
    "regions": [],
    "log_type": "postgres",
    "latency": 0,
    "log_count": null,
    "logs": [],
    "auth_user": null
  },
  {
    "id": "1f272b30-0221-4b43-ac1e-da0710bb57fb",
    "date": "2026-06-30T05:15:02.817Z",
    "timestamp": "2026-06-30T05:15:02.817000",
    "level": "success",
    "status": "00000",
    "method": "",
    "pathname": "",
    "event_message": "connection received: host=2406:da18:96a:8200:518d:124:49d5:f714 port=52906",
    "headers": {},
    "regions": [],
    "log_type": "postgres",
    "latency": 0,
    "log_count": null,
    "logs": [],
    "auth_user": null
  },
  {
    "id": "9396e925-86f0-4795-8a37-80cbcafa02d7",
    "date": "2026-06-30T05:15:02.742Z",
    "timestamp": "2026-06-30T05:15:02.742000",
    "level": "success",
    "status": "00000",
    "method": "",
    "pathname": "",
    "event_message": "connection received: host=2406:da18:96a:8201:f20f:fed0:3cb3:ee58 port=42430",
    "headers": {},
    "regions": [],
    "log_type": "postgres",
    "latency": 0,
    "log_count": null,
    "logs": [],
    "auth_user": null
  },
  {
    "id": "f0e65344-46eb-4716-bd29-c9f42dc7a500",
    "date": "2026-06-30T05:14:45.080Z",
    "timestamp": "2026-06-30T05:14:45.080000",
    "level": "success",
    "status": "00000",
    "method": "",
    "pathname": "",
    "event_message": "connection received: host=2406:da18:96a:8201:16c4:feb5:7c6:34bd port=44938",
    "headers": {},
    "regions": [],
    "log_type": "postgres",
    "latency": 0,
    "log_count": null,
    "logs": [],
    "auth_user": null
  },
  {
    "id": "87ce9331-9e29-42ad-bf7a-9b205da65990",
    "date": "2026-06-30T05:14:45.076Z",
    "timestamp": "2026-06-30T05:14:45.076000",
    "level": "success",
    "status": "00000",
    "method": "",
    "pathname": "",
    "event_message": "connection received: host=2406:da18:96a:8201:aace:dad2:1deb:f404 port=47974",
    "headers": {},
    "regions": [],
    "log_type": "postgres",
    "latency": 0,
    "log_count": null,
    "logs": [],
    "auth_user": null
  },
  {
    "id": "46fabd37-f642-43a2-90bd-fe0ad377a93e",
    "date": "2026-06-30T05:14:04.361Z",
    "timestamp": "2026-06-30T05:14:04.361608",
    "level": "success",
    "status": 200,
    "method": "",
    "pathname": "",
    "event_message": "Warp server error: Thread killed by timeout manager",
    "headers": {},
    "regions": [],
    "log_type": "postgrest",
    "latency": 0,
    "log_count": null,
    "logs": [],
    "auth_user": null
  },
  {
    "id": "8f12072c-3474-44be-99b8-72af9542be91",
    "date": "2026-06-30T05:14:04.360Z",
    "timestamp": "2026-06-30T05:14:04.360056",
    "level": "success",
    "status": 200,
    "method": "",
    "pathname": "",
    "event_message": "Warp server error: Thread killed by timeout manager",
    "headers": {},
    "regions": [],
    "log_type": "postgrest",
    "latency": 0,
    "log_count": null,
    "logs": [],
    "auth_user": null
  },
  {
    "id": "ccf9fddc-2d26-4085-9249-bf4533447046",
    "date": "2026-06-30T05:13:21.002Z",
    "timestamp": "2026-06-30T05:13:21.002000",
    "level": "error",
    "status": "3D000",
    "method": "",
    "pathname": "",
    "event_message": "database \"supabase_admin\" does not exist",
    "headers": {},
    "regions": [],
    "log_type": "postgres",
    "latency": 0,
    "log_count": null,
    "logs": [],
    "auth_user": null
  },
  {
    "id": "e2ee07e8-c475-48b3-b8b1-4981be8d5a3e",
    "date": "2026-06-30T05:13:17.110Z",
    "timestamp": "2026-06-30T05:13:17.110000",
    "level": "error",
    "status": "3D000",
    "method": "",
    "pathname": "",
    "event_message": "database \"supabase_admin\" does not exist",
    "headers": {},
    "regions": [],
    "log_type": "postgres",
    "latency": 0,
    "log_count": null,
    "logs": [],
    "auth_user": null
  },
  {
    "id": "68d50f49-1b03-4069-9c87-2aa252602f4c",
    "date": "2026-06-30T05:13:16.665Z",
    "timestamp": "2026-06-30T05:13:16.665000",
    "level": "error",
    "status": "42P01",
    "method": "",
    "pathname": "",
    "event_message": "relation \"supabase_migrations.schema_migrations\" does not exist",
    "headers": {},
    "regions": [],
    "log_type": "postgres",
    "latency": 0,
    "log_count": null,
    "logs": [],
    "auth_user": null
  },
  {
    "id": "1ddd9ec2-954a-4108-87c3-4c99fc0da41e",
    "date": "2026-06-30T05:13:16.595Z",
    "timestamp": "2026-06-30T05:13:16.595000",
    "level": "success",
    "status": "00000",
    "method": "",
    "pathname": "",
    "event_message": "connection authenticated: identity=\"postgres\" method=scram-sha-256 (/etc/postgresql/pg_hba.conf:97)",
    "headers": {},
    "regions": [],
    "log_type": "postgres",
    "latency": 0,
    "log_count": null,
    "logs": [],
    "auth_user": null
  },
  {
    "id": "d0de015c-d4e6-4478-a0a6-7f1b3c47aeb2",
    "date": "2026-06-30T05:13:16.497Z",
    "timestamp": "2026-06-30T05:13:16.497000",
    "level": "success",
    "status": "00000",
    "method": "",
    "pathname": "",
    "event_message": "connection authenticated: identity=\"postgres\" method=scram-sha-256 (/etc/postgresql/pg_hba.conf:97)",
    "headers": {},
    "regions": [],
    "log_type": "postgres",
    "latency": 0,
    "log_count": null,
    "logs": [],
    "auth_user": null
  },
  {
    "id": "c52b3b53-587a-4f42-b590-4464d924b306",
    "date": "2026-06-30T05:13:16.291Z",
    "timestamp": "2026-06-30T05:13:16.291000",
    "level": "success",
    "status": "00000",
    "method": "",
    "pathname": "",
    "event_message": "connection authenticated: identity=\"postgres\" method=scram-sha-256 (/etc/postgresql/pg_hba.conf:97)",
    "headers": {},
    "regions": [],
    "log_type": "postgres",
    "latency": 0,
    "log_count": null,
    "logs": [],
    "auth_user": null
  },
  {
    "id": "a1867137-5ff4-4054-b809-676dc3cd0381",
    "date": "2026-06-30T05:13:16.259Z",
    "timestamp": "2026-06-30T05:13:16.259000",
    "level": "success",
    "status": "00000",
    "method": "",
    "pathname": "",
    "event_message": "connection authenticated: identity=\"postgres\" method=scram-sha-256 (/etc/postgresql/pg_hba.conf:97)",
    "headers": {},
    "regions": [],
    "log_type": "postgres",
    "latency": 0,
    "log_count": null,
    "logs": [],
    "auth_user": null
  },
  {
    "id": "bf21101a-e378-496a-8814-2c47c1beb406",
    "date": "2026-06-30T05:13:16.246Z",
    "timestamp": "2026-06-30T05:13:16.246000",
    "level": "success",
    "status": "00000",
    "method": "",
    "pathname": "",
    "event_message": "connection authenticated: identity=\"postgres\" method=scram-sha-256 (/etc/postgresql/pg_hba.conf:97)",
    "headers": {},
    "regions": [],
    "log_type": "postgres",
    "latency": 0,
    "log_count": null,
    "logs": [],
    "auth_user": null
  },
  {
    "id": "f38bbba0-1081-4643-ab6d-01a3093c273e",
    "date": "2026-06-30T05:13:16.145Z",
    "timestamp": "2026-06-30T05:13:16.145000",
    "level": "success",
    "status": "00000",
    "method": "",
    "pathname": "",
    "event_message": "connection received: host=2406:da18:96a:8200:7a0f:556d:10b6:4f87 port=33050",
    "headers": {},
    "regions": [],
    "log_type": "postgres",
    "latency": 0,
    "log_count": null,
    "logs": [],
    "auth_user": null
  },
  {
    "id": "deebf340-5445-47ba-a2cb-f891f5b49bcf",
    "date": "2026-06-30T05:13:16.117Z",
    "timestamp": "2026-06-30T05:13:16.117000",
    "level": "success",
    "status": "00000",
    "method": "",
    "pathname": "",
    "event_message": "connection received: host=2406:da18:96a:8201:3d8d:d8dd:5705:ff3b port=59152",
    "headers": {},
    "regions": [],
    "log_type": "postgres",
    "latency": 0,
    "log_count": null,
    "logs": [],
    "auth_user": null
  },
  {
    "id": "8dc23e8d-d5af-4506-9856-45c66576c02e",
    "date": "2026-06-30T05:13:15.969Z",
    "timestamp": "2026-06-30T05:13:15.969000",
    "level": "success",
    "status": "00000",
    "method": "",
    "pathname": "",
    "event_message": "connection received: host=2406:da18:96a:8201:f06c:42ed:1c29:4b7e port=41284",
    "headers": {},
    "regions": [],
    "log_type": "postgres",
    "latency": 0,
    "log_count": null,
    "logs": [],
    "auth_user": null
  },
  {
    "id": "e283c884-443c-4f09-ba6b-a4251676ffbf",
    "date": "2026-06-30T05:13:15.941Z",
    "timestamp": "2026-06-30T05:13:15.941000",
    "level": "success",
    "status": "00000",
    "method": "",
    "pathname": "",
    "event_message": "connection received: host=2406:da18:96a:8200:fa9:489a:faf1:9569 port=41296",
    "headers": {},
    "regions": [],
    "log_type": "postgres",
    "latency": 0,
    "log_count": null,
    "logs": [],
    "auth_user": null
  },
  {
    "id": "d2ddcee0-ef69-4732-ba7d-8263df40d66b",
    "date": "2026-06-30T05:13:15.930Z",
    "timestamp": "2026-06-30T05:13:15.930000",
    "level": "success",
    "status": "00000",
    "method": "",
    "pathname": "",
    "event_message": "connection received: host=2406:da18:96a:8201:f94:51c5:e959:32e0 port=41268",
    "headers": {},
    "regions": [],
    "log_type": "postgres",
    "latency": 0,
    "log_count": null,
    "logs": [],
    "auth_user": null
  },
  {
    "id": "d729bcc5-fffb-4df0-8b69-dea655a2c81f",
    "date": "2026-06-30T05:13:15.924Z",
    "timestamp": "2026-06-30T05:13:15.924000",
    "level": "success",
    "status": "00000",
    "method": "",
    "pathname": "",
    "event_message": "connection received: host=2406:da18:96a:8200:6c6f:1eb7:2183:3605 port=39348",
    "headers": {},
    "regions": [],
    "log_type": "postgres",
    "latency": 0,
    "log_count": null,
    "logs": [],
    "auth_user": null
  },
  {
    "id": "fef5d600-8bdc-427d-bbec-1da2262856cb",
    "date": "2026-06-30T05:13:15.909Z",
    "timestamp": "2026-06-30T05:13:15.909000",
    "level": "success",
    "status": "00000",
    "method": "",
    "pathname": "",
    "event_message": "connection received: host=2406:da18:96a:8201:f20f:fed0:3cb3:ee58 port=55828",
    "headers": {},
    "regions": [],
    "log_type": "postgres",
    "latency": 0,
    "log_count": null,
    "logs": [],
    "auth_user": null
  },
  {
    "id": "2e6cd265-a5b3-4338-9260-8b0bd2a5b1ae",
    "date": "2026-06-30T05:13:15.888Z",
    "timestamp": "2026-06-30T05:13:15.888000",
    "level": "success",
    "status": "00000",
    "method": "",
    "pathname": "",
    "event_message": "connection received: host=2406:da18:96a:8201:f06c:42ed:1c29:4b7e port=41270",
    "headers": {},
    "regions": [],
    "log_type": "postgres",
    "latency": 0,
    "log_count": null,
    "logs": [],
    "auth_user": null
  },
  {
    "id": "b29734d3-d6d7-4e6e-b7b1-f6cfdc6393a6",
    "date": "2026-06-30T05:13:10.858Z",
    "timestamp": "2026-06-30T05:13:10.858000",
    "level": "warning",
    "status": "400",
    "method": "POST",
    "pathname": "/rest/v1/agendas",
    "event_message": "POST | 400 | https://pgvjjtkkphjywusgfmnm.supabase.co/rest/v1/agendas?select=* | node",
    "headers": {},
    "regions": [],
    "log_type": "postgrest",
    "latency": 0,
    "log_count": null,
    "logs": [],
    "auth_user": null
  },
  {
    "id": "e8babd44-1f1b-49fd-8e58-2cda1a0a1a20",
    "date": "2026-06-30T05:13:04.162Z",
    "timestamp": "2026-06-30T05:13:04.162000",
    "level": "warning",
    "status": "400",
    "method": "POST",
    "pathname": "/rest/v1/agendas",
    "event_message": "POST | 400 | https://pgvjjtkkphjywusgfmnm.supabase.co/rest/v1/agendas?select=* | node",
    "headers": {},
    "regions": [],
    "log_type": "postgrest",
    "latency": 0,
    "log_count": null,
    "logs": [],
    "auth_user": null
  },
  {
    "id": "75d3f19f-c4f9-4703-832b-001c7e1d0f0c",
    "date": "2026-06-30T05:12:52.569Z",
    "timestamp": "2026-06-30T05:12:52.569970",
    "level": "success",
    "status": 200,
    "method": "",
    "pathname": "",
    "event_message": "Warp server error: Thread killed by timeout manager",
    "headers": {},
    "regions": [],
    "log_type": "postgrest",
    "latency": 0,
    "log_count": null,
    "logs": [],
    "auth_user": null
  },
  {
    "id": "6df6cdb4-328a-432d-9560-ec3f1f517e54",
    "date": "2026-06-30T05:11:56.959Z",
    "timestamp": "2026-06-30T05:11:56.959000",
    "level": "success",
    "status": "200",
    "method": "GET",
    "pathname": "/rest/v1/agendas",
    "event_message": "GET | 200 | https://pgvjjtkkphjywusgfmnm.supabase.co/rest/v1/agendas?select=*&order=created_at.desc | node",
    "headers": {},
    "regions": [],
    "log_type": "postgrest",
    "latency": 0,
    "log_count": null,
    "logs": [],
    "auth_user": null
  },
  {
    "id": "a661f0d5-7156-4f8b-8e31-7f7ea3e67478",
    "date": "2026-06-30T05:11:49.519Z",
    "timestamp": "2026-06-30T05:11:49.519000",
    "level": "success",
    "status": "200",
    "method": "GET",
    "pathname": "/rest/v1/agendas",
    "event_message": "GET | 200 | https://pgvjjtkkphjywusgfmnm.supabase.co/rest/v1/agendas?select=*&order=created_at.desc&limit=5 | node",
    "headers": {},
    "regions": [],
    "log_type": "postgrest",
    "latency": 0,
    "log_count": null,
    "logs": [],
    "auth_user": null
  },
  {
    "id": "c783011e-ffa6-4246-ac3a-88adf8d2ccc0",
    "date": "2026-06-30T05:11:48.837Z",
    "timestamp": "2026-06-30T05:11:48.837000",
    "level": "success",
    "status": "200",
    "method": "GET",
    "pathname": "/rest/v1/agendas",
    "event_message": "GET | 200 | https://pgvjjtkkphjywusgfmnm.supabase.co/rest/v1/agendas?select=*&order=created_at.desc&limit=5 | node",
    "headers": {},
    "regions": [],
    "log_type": "postgrest",
    "latency": 0,
    "log_count": null,
    "logs": [],
    "auth_user": null
  },
  {
    "id": "91b7d805-cea1-4ba7-8c54-b463868e46fa",
    "date": "2026-06-30T05:11:48.829Z",
    "timestamp": "2026-06-30T05:11:48.829000",
    "level": "success",
    "status": "200",
    "method": "HEAD",
    "pathname": "/rest/v1/active_student_votes",
    "event_message": "HEAD | 200 | https://pgvjjtkkphjywusgfmnm.supabase.co/rest/v1/active_student_votes?select=id | node",
    "headers": {},
    "regions": [],
    "log_type": "postgrest",
    "latency": 0,
    "log_count": null,
    "logs": [],
    "auth_user": null
  },
  {
    "id": "d426d1ef-0ee6-4a47-bbcd-4c99a45f2c11",
    "date": "2026-06-30T05:11:48.828Z",
    "timestamp": "2026-06-30T05:11:48.828000",
    "level": "success",
    "status": "200",
    "method": "HEAD",
    "pathname": "/rest/v1/members",
    "event_message": "HEAD | 200 | https://pgvjjtkkphjywusgfmnm.supabase.co/rest/v1/members?select=id | node",
    "headers": {},
    "regions": [],
    "log_type": "postgrest",
    "latency": 0,
    "log_count": null,
    "logs": [],
    "auth_user": null
  },
  {
    "id": "60e27f94-9055-40ad-85ee-086e11f95642",
    "date": "2026-06-30T05:11:48.828Z",
    "timestamp": "2026-06-30T05:11:48.828000",
    "level": "success",
    "status": "200",
    "method": "HEAD",
    "pathname": "/rest/v1/agendas",
    "event_message": "HEAD | 200 | https://pgvjjtkkphjywusgfmnm.supabase.co/rest/v1/agendas?select=id | node",
    "headers": {},
    "regions": [],
    "log_type": "postgrest",
    "latency": 0,
    "log_count": null,
    "logs": [],
    "auth_user": null
  },
  {
    "id": "cc197001-921f-4e5b-8f70-d19a000e6f0c",
    "date": "2026-06-30T05:11:48.660Z",
    "timestamp": "2026-06-30T05:11:48.660000",
    "level": "success",
    "status": "00000",
    "method": "",
    "pathname": "",
    "event_message": "connection authorized: user=authenticator database=postgres application_name=PostgREST 14.5 SSL enabled (protocol=TLSv1.3, cipher=TLS_AES_256_GCM_SHA384, bits=256)",
    "headers": {},
    "regions": [],
    "log_type": "postgres",
    "latency": 0,
    "log_count": null,
    "logs": [],
    "auth_user": null
  },
  {
    "id": "9974458f-34af-46c9-a2e3-7aeee8f6ddd6",
    "date": "2026-06-30T05:11:48.287Z",
    "timestamp": "2026-06-30T05:11:48.287000",
    "level": "success",
    "status": "00000",
    "method": "",
    "pathname": "",
    "event_message": "connection authorized: user=authenticator database=postgres application_name=PostgREST 14.5 SSL enabled (protocol=TLSv1.3, cipher=TLS_AES_256_GCM_SHA384, bits=256)",
    "headers": {},
    "regions": [],
    "log_type": "postgres",
    "latency": 0,
    "log_count": null,
    "logs": [],
    "auth_user": null
  },
  {
    "id": "e54f44b0-d918-4fb7-877f-d736e57e906f",
    "date": "2026-06-30T05:11:48.174Z",
    "timestamp": "2026-06-30T05:11:48.174000",
    "level": "success",
    "status": "200",
    "method": "HEAD",
    "pathname": "/rest/v1/active_student_votes",
    "event_message": "HEAD | 200 | https://pgvjjtkkphjywusgfmnm.supabase.co/rest/v1/active_student_votes?select=id | node",
    "headers": {},
    "regions": [],
    "log_type": "postgrest",
    "latency": 0,
    "log_count": null,
    "logs": [],
    "auth_user": null
  },
  {
    "id": "8ed77e97-fcef-4ba7-98c8-a8ee150b6d3d",
    "date": "2026-06-30T05:11:48.173Z",
    "timestamp": "2026-06-30T05:11:48.173000",
    "level": "success",
    "status": "200",
    "method": "HEAD",
    "pathname": "/rest/v1/agendas",
    "event_message": "HEAD | 200 | https://pgvjjtkkphjywusgfmnm.supabase.co/rest/v1/agendas?select=id | node",
    "headers": {},
    "regions": [],
    "log_type": "postgrest",
    "latency": 0,
    "log_count": null,
    "logs": [],
    "auth_user": null
  },
  {
    "id": "421e74b1-7aa8-4e77-a452-a910456e8085",
    "date": "2026-06-30T05:11:48.157Z",
    "timestamp": "2026-06-30T05:11:48.157000",
    "level": "success",
    "status": "200",
    "method": "HEAD",
    "pathname": "/rest/v1/members",
    "event_message": "HEAD | 200 | https://pgvjjtkkphjywusgfmnm.supabase.co/rest/v1/members?select=id | node",
    "headers": {},
    "regions": [],
    "log_type": "postgrest",
    "latency": 0,
    "log_count": null,
    "logs": [],
    "auth_user": null
  },
  {
    "id": "68bc223c-f2b3-4011-a882-04c58a427540",
    "date": "2026-06-30T05:11:46.946Z",
    "timestamp": "2026-06-30T05:11:46.946000",
    "level": "success",
    "status": "00000",
    "method": "",
    "pathname": "",
    "event_message": "connection authorized: user=authenticator database=postgres application_name=PostgREST 14.5 SSL enabled (protocol=TLSv1.3, cipher=TLS_AES_256_GCM_SHA384, bits=256)",
    "headers": {},
    "regions": [],
    "log_type": "postgres",
    "latency": 0,
    "log_count": null,
    "logs": [],
    "auth_user": null
  },
  {
    "id": "398e443e-04ff-47e1-ab59-09c778f3812c",
    "date": "2026-06-30T05:11:46.427Z",
    "timestamp": "2026-06-30T05:11:46.427000",
    "level": "success",
    "status": "200",
    "method": "GET",
    "pathname": "/rest/v1/members",
    "event_message": "GET | 200 | https://pgvjjtkkphjywusgfmnm.supabase.co/rest/v1/members?select=*&full_name=ilike.Moh+Bagus+Jiran+Riskohar&nim=eq.24550011 | node",
    "headers": {},
    "regions": [],
    "log_type": "postgrest",
    "latency": 0,
    "log_count": null,
    "logs": [],
    "auth_user": null
  },
  {
    "id": "56c306b4-7071-462f-95fe-53d7f2e37041",
    "date": "2026-06-30T05:11:22.572Z",
    "timestamp": "2026-06-30T05:11:22.572650",
    "level": "success",
    "status": 200,
    "method": "",
    "pathname": "",
    "event_message": "Warp server error: Thread killed by timeout manager",
    "headers": {},
    "regions": [],
    "log_type": "postgrest",
    "latency": 0,
    "log_count": null,
    "logs": [],
    "auth_user": null
  },
  {
    "id": "e9dd18c7-8973-456e-9976-d8c5526e0aa7",
    "date": "2026-06-30T05:11:07.182Z",
    "timestamp": "2026-06-30T05:11:07.182000",
    "level": "success",
    "status": "00000",
    "method": "",
    "pathname": "",
    "event_message": "connection authorized: user=authenticator database=postgres application_name=PostgREST 14.5 SSL enabled (protocol=TLSv1.3, cipher=TLS_AES_256_GCM_SHA384, bits=256)",
    "headers": {},
    "regions": [],
    "log_type": "postgres",
    "latency": 0,
    "log_count": null,
    "logs": [],
    "auth_user": null
  },
  {
    "id": "33f22e7f-f4f9-47e7-871d-c224415537f9",
    "date": "2026-06-30T05:11:06.659Z",
    "timestamp": "2026-06-30T05:11:06.659000",
    "level": "success",
    "status": "200",
    "method": "GET",
    "pathname": "/rest/v1/members",
    "event_message": "GET | 200 | https://pgvjjtkkphjywusgfmnm.supabase.co/rest/v1/members?select=id%2Cfull_name%2Cnim%2Cis_admin&order=full_name.asc | node",
    "headers": {},
    "regions": [],
    "log_type": "postgrest",
    "latency": 0,
    "log_count": null,
    "logs": [],
    "auth_user": null
  },
  {
    "id": "1f777baf-a801-4b72-95b1-69619e01482f",
    "date": "2026-06-30T05:10:51.026Z",
    "timestamp": "2026-06-30T05:10:51.026000",
    "level": "success",
    "status": "200",
    "method": "GET",
    "pathname": "/rest/v1/members",
    "event_message": "GET | 200 | https://pgvjjtkkphjywusgfmnm.supabase.co/rest/v1/members?select=id%2Cfull_name%2Cnim%2Cis_admin&order=full_name.asc | node",
    "headers": {},
    "regions": [],
    "log_type": "postgrest",
    "latency": 0,
    "log_count": null,
    "logs": [],
    "auth_user": null
  },
  {
    "id": "29ba57ba-30c6-470a-9c19-404ec165da17",
    "date": "2026-06-30T05:10:50.548Z",
    "timestamp": "2026-06-30T05:10:50.548000",
    "level": "success",
    "status": "200",
    "method": "GET",
    "pathname": "/rest/v1/members",
    "event_message": "GET | 200 | https://pgvjjtkkphjywusgfmnm.supabase.co/rest/v1/members?select=id%2Cfull_name%2Cnim%2Cis_admin&order=full_name.asc | node",
    "headers": {},
    "regions": [],
    "log_type": "postgrest",
    "latency": 0,
    "log_count": null,
    "logs": [],
    "auth_user": null
  },
  {
    "id": "3b88833d-a555-4abb-b830-d0b2dafa9bc5",
    "date": "2026-06-30T05:10:49.052Z",
    "timestamp": "2026-06-30T05:10:49.052000",
    "level": "success",
    "status": "00000",
    "method": "",
    "pathname": "",
    "event_message": "checkpoint complete: wrote 4 buffers (0.0%); 0 WAL file(s) added, 0 removed, 2 recycled; write=0.331 s, sync=0.002 s, total=0.345 s; sync files=4, longest=0.002 s, average=0.001 s; distance=32768 kB, estimate=32768 kB; lsn=0/D000080, redo lsn=0/D000028",
    "headers": {},
    "regions": [],
    "log_type": "postgres",
    "latency": 0,
    "log_count": null,
    "logs": [],
    "auth_user": null
  },
  {
    "id": "3d0c08f0-73d9-4276-839e-e364803dfce7",
    "date": "2026-06-30T05:10:48.708Z",
    "timestamp": "2026-06-30T05:10:48.708000",
    "level": "success",
    "status": "00000",
    "method": "",
    "pathname": "",
    "event_message": "checkpoint starting: time",
    "headers": {},
    "regions": [],
    "log_type": "postgres",
    "latency": 0,
    "log_count": null,
    "logs": [],
    "auth_user": null
  },
  {
    "id": "056be134-8e4d-4330-9758-49ddaa007e29",
    "date": "2026-06-30T05:10:36.046Z",
    "timestamp": "2026-06-30T05:10:36.046000",
    "level": "success",
    "status": "200",
    "method": "GET",
    "pathname": "/rest/v1/agendas",
    "event_message": "GET | 200 | https://pgvjjtkkphjywusgfmnm.supabase.co/rest/v1/agendas?select=*&order=created_at.desc&limit=5 | node",
    "headers": {},
    "regions": [],
    "log_type": "postgrest",
    "latency": 0,
    "log_count": null,
    "logs": [],
    "auth_user": null
  },
  {
    "id": "455c5402-111c-4711-8bdb-3e947c70bb49",
    "date": "2026-06-30T05:10:35.847Z",
    "timestamp": "2026-06-30T05:10:35.847000",
    "level": "success",
    "status": "00000",
    "method": "",
    "pathname": "",
    "event_message": "connection authorized: user=authenticator database=postgres application_name=PostgREST 14.5 SSL enabled (protocol=TLSv1.3, cipher=TLS_AES_256_GCM_SHA384, bits=256)",
    "headers": {},
    "regions": [],
    "log_type": "postgres",
    "latency": 0,
    "log_count": null,
    "logs": [],
    "auth_user": null
  },
  {
    "id": "ba55d827-1ac5-48dc-b270-f3aeee418190",
    "date": "2026-06-30T05:10:35.846Z",
    "timestamp": "2026-06-30T05:10:35.846000",
    "level": "success",
    "status": "00000",
    "method": "",
    "pathname": "",
    "event_message": "connection authorized: user=authenticator database=postgres application_name=PostgREST 14.5 SSL enabled (protocol=TLSv1.3, cipher=TLS_AES_256_GCM_SHA384, bits=256)",
    "headers": {},
    "regions": [],
    "log_type": "postgres",
    "latency": 0,
    "log_count": null,
    "logs": [],
    "auth_user": null
  },
  {
    "id": "37f70c08-438c-4178-89cd-ce459c45b718",
    "date": "2026-06-30T05:10:35.846Z",
    "timestamp": "2026-06-30T05:10:35.846000",
    "level": "success",
    "status": "00000",
    "method": "",
    "pathname": "",
    "event_message": "connection authorized: user=authenticator database=postgres application_name=PostgREST 14.5 SSL enabled (protocol=TLSv1.3, cipher=TLS_AES_256_GCM_SHA384, bits=256)",
    "headers": {},
    "regions": [],
    "log_type": "postgres",
    "latency": 0,
    "log_count": null,
    "logs": [],
    "auth_user": null
  },
  {
    "id": "3b0d0152-5b16-4216-9bc6-8012a7cdfab9",
    "date": "2026-06-30T05:10:35.039Z",
    "timestamp": "2026-06-30T05:10:35.039000",
    "level": "success",
    "status": "200",
    "method": "HEAD",
    "pathname": "/rest/v1/agendas",
    "event_message": "HEAD | 200 | https://pgvjjtkkphjywusgfmnm.supabase.co/rest/v1/agendas?select=id | node",
    "headers": {},
    "regions": [],
    "log_type": "postgrest",
    "latency": 0,
    "log_count": null,
    "logs": [],
    "auth_user": null
  },
  {
    "id": "57e02393-c85c-4071-8e27-722abfe87bcb",
    "date": "2026-06-30T05:10:35.037Z",
    "timestamp": "2026-06-30T05:10:35.037000",
    "level": "success",
    "status": "200",
    "method": "HEAD",
    "pathname": "/rest/v1/active_student_votes",
    "event_message": "HEAD | 200 | https://pgvjjtkkphjywusgfmnm.supabase.co/rest/v1/active_student_votes?select=id | node",
    "headers": {},
    "regions": [],
    "log_type": "postgrest",
    "latency": 0,
    "log_count": null,
    "logs": [],
    "auth_user": null
  },
  {
    "id": "6cce8c58-bcbc-4d85-a631-94e983285e6c",
    "date": "2026-06-30T05:10:35.031Z",
    "timestamp": "2026-06-30T05:10:35.031000",
    "level": "success",
    "status": "200",
    "method": "HEAD",
    "pathname": "/rest/v1/members",
    "event_message": "HEAD | 200 | https://pgvjjtkkphjywusgfmnm.supabase.co/rest/v1/members?select=id | node",
    "headers": {},
    "regions": [],
    "log_type": "postgrest",
    "latency": 0,
    "log_count": null,
    "logs": [],
    "auth_user": null
  },
  {
    "id": "e132b532-9756-4ddc-8c33-494458dc931e",
    "date": "2026-06-30T05:07:37.946Z",
    "timestamp": "2026-06-30T05:07:37.946000",
    "level": "success",
    "status": "00000",
    "method": "",
    "pathname": "",
    "event_message": "connection authenticated: identity=\"postgres\" method=scram-sha-256 (/etc/postgresql/pg_hba.conf:97)",
    "headers": {},
    "regions": [],
    "log_type": "postgres",
    "latency": 0,
    "log_count": null,
    "logs": [],
    "auth_user": null
  },
  {
    "id": "a88705bc-7e5d-43b3-a694-70d61baff48c",
    "date": "2026-06-30T05:07:37.843Z",
    "timestamp": "2026-06-30T05:07:37.843000",
    "level": "error",
    "status": "42P01",
    "method": "",
    "pathname": "",
    "event_message": "relation \"supabase_migrations.schema_migrations\" does not exist",
    "headers": {},
    "regions": [],
    "log_type": "postgres",
    "latency": 0,
    "log_count": null,
    "logs": [],
    "auth_user": null
  },
  {
    "id": "3530e11d-0745-4b49-8a53-6eaaf2a50cba",
    "date": "2026-06-30T05:07:37.772Z",
    "timestamp": "2026-06-30T05:07:37.772000",
    "level": "success",
    "status": "00000",
    "method": "",
    "pathname": "",
    "event_message": "connection authenticated: identity=\"postgres\" method=scram-sha-256 (/etc/postgresql/pg_hba.conf:97)",
    "headers": {},
    "regions": [],
    "log_type": "postgres",
    "latency": 0,
    "log_count": null,
    "logs": [],
    "auth_user": null
  },
  {
    "id": "ca918cce-ed50-4bd0-a206-ba5f7db666e2",
    "date": "2026-06-30T05:07:37.567Z",
    "timestamp": "2026-06-30T05:07:37.567000",
    "level": "success",
    "status": "00000",
    "method": "",
    "pathname": "",
    "event_message": "connection authorized: user=pgbouncer database=postgres SSL enabled (protocol=TLSv1.3, cipher=TLS_AES_256_GCM_SHA384, bits=256)",
    "headers": {},
    "regions": [],
    "log_type": "postgres",
    "latency": 0,
    "log_count": null,
    "logs": [],
    "auth_user": null
  },
  {
    "id": "d6921095-7099-4f19-8dfb-9d15eb60bff2",
    "date": "2026-06-30T05:07:37.566Z",
    "timestamp": "2026-06-30T05:07:37.566000",
    "level": "success",
    "status": "00000",
    "method": "",
    "pathname": "",
    "event_message": "connection authenticated: user=\"pgbouncer\" method=trust (/etc/postgresql/pg_hba.conf:87)",
    "headers": {},
    "regions": [],
    "log_type": "postgres",
    "latency": 0,
    "log_count": null,
    "logs": [],
    "auth_user": null
  },
  {
    "id": "d93c97f9-517c-4648-867c-2db014198b7b",
    "date": "2026-06-30T05:07:37.416Z",
    "timestamp": "2026-06-30T05:07:37.416000",
    "level": "success",
    "status": "00000",
    "method": "",
    "pathname": "",
    "event_message": "connection received: host=2406:da18:96a:8200:97f5:c560:c9cb:9767 port=48542",
    "headers": {},
    "regions": [],
    "log_type": "postgres",
    "latency": 0,
    "log_count": null,
    "logs": [],
    "auth_user": null
  },
  {
    "id": "47be9dc9-44c6-4ce0-8fc7-3f4b865aefec",
    "date": "2026-06-30T05:07:09.953Z",
    "timestamp": "2026-06-30T05:07:09.953000",
    "level": "success",
    "status": "00000",
    "method": "",
    "pathname": "",
    "event_message": "connection authenticated: identity=\"postgres\" method=scram-sha-256 (/etc/postgresql/pg_hba.conf:97)",
    "headers": {},
    "regions": [],
    "log_type": "postgres",
    "latency": 0,
    "log_count": null,
    "logs": [],
    "auth_user": null
  },
  {
    "id": "2a0eba77-cbf7-47e8-947e-21caa5cfde4c",
    "date": "2026-06-30T05:07:09.603Z",
    "timestamp": "2026-06-30T05:07:09.603000",
    "level": "success",
    "status": "00000",
    "method": "",
    "pathname": "",
    "event_message": "connection received: host=2406:da18:96a:8200:fa9:489a:faf1:9569 port=55004",
    "headers": {},
    "regions": [],
    "log_type": "postgres",
    "latency": 0,
    "log_count": null,
    "logs": [],
    "auth_user": null
  },
  {
    "id": "ee0dbda7-a47d-4b2f-b3eb-6170c12b1e70",
    "date": "2026-06-30T05:06:57.475Z",
    "timestamp": "2026-06-30T05:06:57.475000",
    "level": "success",
    "status": "00000",
    "method": "",
    "pathname": "",
    "event_message": "connection authenticated: identity=\"postgres\" method=scram-sha-256 (/etc/postgresql/pg_hba.conf:97)",
    "headers": {},
    "regions": [],
    "log_type": "postgres",
    "latency": 0,
    "log_count": null,
    "logs": [],
    "auth_user": null
  },
  {
    "id": "11142f64-046e-402b-ae80-791eae30dd87",
    "date": "2026-06-30T05:06:57.436Z",
    "timestamp": "2026-06-30T05:06:57.436000",
    "level": "success",
    "status": "00000",
    "method": "",
    "pathname": "",
    "event_message": "connection authenticated: identity=\"postgres\" method=scram-sha-256 (/etc/postgresql/pg_hba.conf:97)",
    "headers": {},
    "regions": [],
    "log_type": "postgres",
    "latency": 0,
    "log_count": null,
    "logs": [],
    "auth_user": null
  },
  {
    "id": "6377960d-efa3-4e9f-acab-84149f898bcd",
    "date": "2026-06-30T05:06:57.422Z",
    "timestamp": "2026-06-30T05:06:57.422000",
    "level": "success",
    "status": "00000",
    "method": "",
    "pathname": "",
    "event_message": "connection authenticated: identity=\"postgres\" method=scram-sha-256 (/etc/postgresql/pg_hba.conf:97)",
    "headers": {},
    "regions": [],
    "log_type": "postgres",
    "latency": 0,
    "log_count": null,
    "logs": [],
    "auth_user": null
  },
  {
    "id": "eaa7cc59-40fb-465a-8641-5b5b94eb2a6f",
    "date": "2026-06-30T05:06:57.409Z",
    "timestamp": "2026-06-30T05:06:57.409000",
    "level": "success",
    "status": "00000",
    "method": "",
    "pathname": "",
    "event_message": "connection authenticated: identity=\"postgres\" method=scram-sha-256 (/etc/postgresql/pg_hba.conf:97)",
    "headers": {},
    "regions": [],
    "log_type": "postgres",
    "latency": 0,
    "log_count": null,
    "logs": [],
    "auth_user": null
  },
  {
    "id": "0e48cd22-276b-4bdb-b45a-ccef90a5230a",
    "date": "2026-06-30T05:06:57.377Z",
    "timestamp": "2026-06-30T05:06:57.377000",
    "level": "success",
    "status": "00000",
    "method": "",
    "pathname": "",
    "event_message": "connection authenticated: identity=\"postgres\" method=scram-sha-256 (/etc/postgresql/pg_hba.conf:97)",
    "headers": {},
    "regions": [],
    "log_type": "postgres",
    "latency": 0,
    "log_count": null,
    "logs": [],
    "auth_user": null
  },
  {
    "id": "f87bc335-1f71-460f-9fd5-e463acff172d",
    "date": "2026-06-30T05:06:57.103Z",
    "timestamp": "2026-06-30T05:06:57.103000",
    "level": "success",
    "status": "00000",
    "method": "",
    "pathname": "",
    "event_message": "connection received: host=2406:da18:96a:8201:368:dded:1c99:9bc8 port=41128",
    "headers": {},
    "regions": [],
    "log_type": "postgres",
    "latency": 0,
    "log_count": null,
    "logs": [],
    "auth_user": null
  },
  {
    "id": "5033d228-59d5-46f8-9885-29859614dfae",
    "date": "2026-06-30T05:06:57.086Z",
    "timestamp": "2026-06-30T05:06:57.086000",
    "level": "success",
    "status": "00000",
    "method": "",
    "pathname": "",
    "event_message": "connection received: host=2406:da18:96a:8201:4ca:9e09:1e81:71e9 port=52022",
    "headers": {},
    "regions": [],
    "log_type": "postgres",
    "latency": 0,
    "log_count": null,
    "logs": [],
    "auth_user": null
  },
  {
    "id": "c876e11a-1d67-475c-9182-fa120e6c382e",
    "date": "2026-06-30T05:06:57.077Z",
    "timestamp": "2026-06-30T05:06:57.077000",
    "level": "success",
    "status": "00000",
    "method": "",
    "pathname": "",
    "event_message": "connection received: host=2406:da18:96a:8201:c3d6:ea88:e88a:ec89 port=34940",
    "headers": {},
    "regions": [],
    "log_type": "postgres",
    "latency": 0,
    "log_count": null,
    "logs": [],
    "auth_user": null
  },
  {
    "id": "58acfe77-470c-4bdb-920b-124d4dfcec9f",
    "date": "2026-06-30T05:06:57.056Z",
    "timestamp": "2026-06-30T05:06:57.056000",
    "level": "success",
    "status": "00000",
    "method": "",
    "pathname": "",
    "event_message": "connection received: host=2406:da18:96a:8201:9a84:9f75:111e:2322 port=52508",
    "headers": {},
    "regions": [],
    "log_type": "postgres",
    "latency": 0,
    "log_count": null,
    "logs": [],
    "auth_user": null
  },
  {
    "id": "dd48f383-8daf-4bbd-9710-ea9d2002a5b6",
    "date": "2026-06-30T05:06:57.024Z",
    "timestamp": "2026-06-30T05:06:57.024000",
    "level": "success",
    "status": "00000",
    "method": "",
    "pathname": "",
    "event_message": "connection received: host=2406:da18:96a:8200:fa9:489a:faf1:9569 port=60094",
    "headers": {},
    "regions": [],
    "log_type": "postgres",
    "latency": 0,
    "log_count": null,
    "logs": [],
    "auth_user": null
  },
  {
    "id": "c68f2000-cf12-4cec-839e-83686708db59",
    "date": "2026-06-30T05:06:50.989Z",
    "timestamp": "2026-06-30T05:06:50.989000",
    "level": "success",
    "status": "00000",
    "method": "",
    "pathname": "",
    "event_message": "connection authenticated: identity=\"postgres\" method=scram-sha-256 (/etc/postgresql/pg_hba.conf:97)",
    "headers": {},
    "regions": [],
    "log_type": "postgres",
    "latency": 0,
    "log_count": null,
    "logs": [],
    "auth_user": null
  },
  {
    "id": "be88d951-66a7-4b2f-90b8-c405b95111be",
    "date": "2026-06-30T05:06:50.969Z",
    "timestamp": "2026-06-30T05:06:50.969000",
    "level": "success",
    "status": "00000",
    "method": "",
    "pathname": "",
    "event_message": "connection authenticated: identity=\"postgres\" method=scram-sha-256 (/etc/postgresql/pg_hba.conf:97)",
    "headers": {},
    "regions": [],
    "log_type": "postgres",
    "latency": 0,
    "log_count": null,
    "logs": [],
    "auth_user": null
  },
  {
    "id": "e214760e-4067-4caf-9c04-9f8db87dcca3",
    "date": "2026-06-30T05:06:50.774Z",
    "timestamp": "2026-06-30T05:06:50.774000",
    "level": "success",
    "status": "00000",
    "method": "",
    "pathname": "",
    "event_message": "connection authenticated: identity=\"postgres\" method=scram-sha-256 (/etc/postgresql/pg_hba.conf:97)",
    "headers": {},
    "regions": [],
    "log_type": "postgres",
    "latency": 0,
    "log_count": null,
    "logs": [],
    "auth_user": null
  },
  {
    "id": "40e87d22-2e51-4f58-9293-849730236273",
    "date": "2026-06-30T05:06:50.640Z",
    "timestamp": "2026-06-30T05:06:50.640000",
    "level": "success",
    "status": "00000",
    "method": "",
    "pathname": "",
    "event_message": "connection received: host=2406:da18:96a:8201:30e:c60a:9dd4:37ce port=49274",
    "headers": {},
    "regions": [],
    "log_type": "postgres",
    "latency": 0,
    "log_count": null,
    "logs": [],
    "auth_user": null
  },
  {
    "id": "fdff9a41-cfe1-464e-aeb8-b587439461a2",
    "date": "2026-06-30T05:06:50.618Z",
    "timestamp": "2026-06-30T05:06:50.618000",
    "level": "success",
    "status": "00000",
    "method": "",
    "pathname": "",
    "event_message": "connection received: host=2406:da18:96a:8201:99bd:396e:218:24dd port=32860",
    "headers": {},
    "regions": [],
    "log_type": "postgres",
    "latency": 0,
    "log_count": null,
    "logs": [],
    "auth_user": null
  },
  {
    "id": "271f466b-2d99-4f04-9d59-937bb5cff397",
    "date": "2026-06-30T05:06:50.420Z",
    "timestamp": "2026-06-30T05:06:50.420000",
    "level": "success",
    "status": "00000",
    "method": "",
    "pathname": "",
    "event_message": "connection received: host=2406:da18:96a:8200:c712:656d:fab9:f6f6 port=39514",
    "headers": {},
    "regions": [],
    "log_type": "postgres",
    "latency": 0,
    "log_count": null,
    "logs": [],
    "auth_user": null
  },
  {
    "id": "1c1cd8a8-6965-4c28-899a-65870f9633a1",
    "date": "2026-06-30T05:04:57.055Z",
    "timestamp": "2026-06-30T05:04:57.055000",
    "level": "success",
    "status": "00000",
    "method": "",
    "pathname": "",
    "event_message": "connection authenticated: identity=\"postgres\" method=scram-sha-256 (/etc/postgresql/pg_hba.conf:97)",
    "headers": {},
    "regions": [],
    "log_type": "postgres",
    "latency": 0,
    "log_count": null,
    "logs": [],
    "auth_user": null
  },
  {
    "id": "be376ca9-3f9d-4390-8001-772a3ed86f63",
    "date": "2026-06-30T05:04:57.045Z",
    "timestamp": "2026-06-30T05:04:57.045000",
    "level": "success",
    "status": "00000",
    "method": "",
    "pathname": "",
    "event_message": "connection authenticated: identity=\"postgres\" method=scram-sha-256 (/etc/postgresql/pg_hba.conf:97)",
    "headers": {},
    "regions": [],
    "log_type": "postgres",
    "latency": 0,
    "log_count": null,
    "logs": [],
    "auth_user": null
  },
  {
    "id": "1e76babe-b54c-4beb-b456-05f4e72879c3",
    "date": "2026-06-30T05:04:57.037Z",
    "timestamp": "2026-06-30T05:04:57.037000",
    "level": "success",
    "status": "00000",
    "method": "",
    "pathname": "",
    "event_message": "connection authenticated: identity=\"postgres\" method=scram-sha-256 (/etc/postgresql/pg_hba.conf:97)",
    "headers": {},
    "regions": [],
    "log_type": "postgres",
    "latency": 0,
    "log_count": null,
    "logs": [],
    "auth_user": null
  },
  {
    "id": "a6dcc800-9c6c-4a37-9148-f711cea939ce",
    "date": "2026-06-30T05:04:56.686Z",
    "timestamp": "2026-06-30T05:04:56.686000",
    "level": "success",
    "status": "00000",
    "method": "",
    "pathname": "",
    "event_message": "connection received: host=2406:da18:96a:8200:ee99:9125:9fe9:ab3 port=37414",
    "headers": {},
    "regions": [],
    "log_type": "postgres",
    "latency": 0,
    "log_count": null,
    "logs": [],
    "auth_user": null
  },
  {
    "id": "60e07952-e40c-433c-8555-380127e08f60",
    "date": "2026-06-30T05:04:56.681Z",
    "timestamp": "2026-06-30T05:04:56.681000",
    "level": "success",
    "status": "00000",
    "method": "",
    "pathname": "",
    "event_message": "connection received: host=2406:da18:96a:8201:c3d6:ea88:e88a:ec89 port=41520",
    "headers": {},
    "regions": [],
    "log_type": "postgres",
    "latency": 0,
    "log_count": null,
    "logs": [],
    "auth_user": null
  },
  {
    "id": "32eb0203-e987-4294-ab11-8e0a0e637043",
    "date": "2026-06-30T05:04:56.680Z",
    "timestamp": "2026-06-30T05:04:56.680000",
    "level": "success",
    "status": "00000",
    "method": "",
    "pathname": "",
    "event_message": "connection received: host=2406:da18:96a:8201:4ca:9e09:1e81:71e9 port=44456",
    "headers": {},
    "regions": [],
    "log_type": "postgres",
    "latency": 0,
    "log_count": null,
    "logs": [],
    "auth_user": null
  },
  {
    "id": "d6de7e8a-2229-428a-b380-d24b23867cb2",
    "date": "2026-06-30T05:03:40.048Z",
    "timestamp": "2026-06-30T05:03:40.048000",
    "level": "success",
    "status": "00000",
    "method": "",
    "pathname": "",
    "event_message": "connection authenticated: identity=\"postgres\" method=scram-sha-256 (/etc/postgresql/pg_hba.conf:97)",
    "headers": {},
    "regions": [],
    "log_type": "postgres",
    "latency": 0,
    "log_count": null,
    "logs": [],
    "auth_user": null
  },
  {
    "id": "55779728-d594-488c-9c74-ad95c12b36c2",
    "date": "2026-06-30T05:03:36.644Z",
    "timestamp": "2026-06-30T05:03:36.644000",
    "level": "success",
    "status": "00000",
    "method": "",
    "pathname": "",
    "event_message": "connection authenticated: identity=\"postgres\" method=scram-sha-256 (/etc/postgresql/pg_hba.conf:97)",
    "headers": {},
    "regions": [],
    "log_type": "postgres",
    "latency": 0,
    "log_count": null,
    "logs": [],
    "auth_user": null
  },
  {
    "id": "56ac032c-031f-4e61-bc5b-3006010da24b",
    "date": "2026-06-30T05:03:36.602Z",
    "timestamp": "2026-06-30T05:03:36.602000",
    "level": "success",
    "status": "00000",
    "method": "",
    "pathname": "",
    "event_message": "connection authenticated: identity=\"postgres\" method=scram-sha-256 (/etc/postgresql/pg_hba.conf:97)",
    "headers": {},
    "regions": [],
    "log_type": "postgres",
    "latency": 0,
    "log_count": null,
    "logs": [],
    "auth_user": null
  },
  {
    "id": "1ef156fd-cdde-46ae-ae78-96f843163863",
    "date": "2026-06-30T05:03:34.572Z",
    "timestamp": "2026-06-30T05:03:34.572000",
    "level": "success",
    "status": "00000",
    "method": "",
    "pathname": "",
    "event_message": "connection received: host=2406:da18:96a:8201:368:dded:1c99:9bc8 port=52658",
    "headers": {},
    "regions": [],
    "log_type": "postgres",
    "latency": 0,
    "log_count": null,
    "logs": [],
    "auth_user": null
  },
  {
    "id": "914f5512-fe38-47d7-b3a6-e252540607c0",
    "date": "2026-06-30T05:03:34.569Z",
    "timestamp": "2026-06-30T05:03:34.569000",
    "level": "success",
    "status": "00000",
    "method": "",
    "pathname": "",
    "event_message": "connection received: host=2406:da18:96a:8201:6a90:68:6a10:489e port=35604",
    "headers": {},
    "regions": [],
    "log_type": "postgres",
    "latency": 0,
    "log_count": null,
    "logs": [],
    "auth_user": null
  },
  {
    "id": "9bf8a882-ce38-4b81-b1c3-6187067d05df",
    "date": "2026-06-30T05:03:22.537Z",
    "timestamp": "2026-06-30T05:03:22.537910",
    "level": "success",
    "status": 200,
    "method": "",
    "pathname": "",
    "event_message": "Warp server error: Thread killed by timeout manager",
    "headers": {},
    "regions": [],
    "log_type": "postgrest",
    "latency": 0,
    "log_count": null,
    "logs": [],
    "auth_user": null
  },
  {
    "id": "0b0cf802-ceda-4b1c-b3ad-bac5d6ead09a",
    "date": "2026-06-30T05:02:26.097Z",
    "timestamp": "2026-06-30T05:02:26.097000",
    "level": "success",
    "status": "200",
    "method": "GET",
    "pathname": "/rest/v1/agendas",
    "event_message": "GET | 200 | https://pgvjjtkkphjywusgfmnm.supabase.co/rest/v1/agendas?select=*&order=created_at.desc&limit=5 | node",
    "headers": {},
    "regions": [],
    "log_type": "postgrest",
    "latency": 0,
    "log_count": null,
    "logs": [],
    "auth_user": null
  },
  {
    "id": "e150702a-0ca1-43a5-99f6-355294526a98",
    "date": "2026-06-30T05:02:23.896Z",
    "timestamp": "2026-06-30T05:02:23.896000",
    "level": "success",
    "status": "00000",
    "method": "",
    "pathname": "",
    "event_message": "connection authorized: user=authenticator database=postgres application_name=PostgREST 14.5 SSL enabled (protocol=TLSv1.3, cipher=TLS_AES_256_GCM_SHA384, bits=256)",
    "headers": {},
    "regions": [],
    "log_type": "postgres",
    "latency": 0,
    "log_count": null,
    "logs": [],
    "auth_user": null
  },
  {
    "id": "e188d67a-bf67-4813-a5cf-591948c97450",
    "date": "2026-06-30T05:02:23.892Z",
    "timestamp": "2026-06-30T05:02:23.892000",
    "level": "success",
    "status": "00000",
    "method": "",
    "pathname": "",
    "event_message": "connection authorized: user=authenticator database=postgres application_name=PostgREST 14.5 SSL enabled (protocol=TLSv1.3, cipher=TLS_AES_256_GCM_SHA384, bits=256)",
    "headers": {},
    "regions": [],
    "log_type": "postgres",
    "latency": 0,
    "log_count": null,
    "logs": [],
    "auth_user": null
  },
  {
    "id": "b55d8fd4-80ec-4bed-8d33-45b73199c6d9",
    "date": "2026-06-30T05:02:23.836Z",
    "timestamp": "2026-06-30T05:02:23.836000",
    "level": "success",
    "status": "00000",
    "method": "",
    "pathname": "",
    "event_message": "connection authorized: user=authenticator database=postgres application_name=PostgREST 14.5 SSL enabled (protocol=TLSv1.3, cipher=TLS_AES_256_GCM_SHA384, bits=256)",
    "headers": {},
    "regions": [],
    "log_type": "postgres",
    "latency": 0,
    "log_count": null,
    "logs": [],
    "auth_user": null
  },
  {
    "id": "3e8c194e-cfac-4a32-8595-10214de27d97",
    "date": "2026-06-30T05:02:23.492Z",
    "timestamp": "2026-06-30T05:02:23.492000",
    "level": "success",
    "status": "200",
    "method": "HEAD",
    "pathname": "/rest/v1/agendas",
    "event_message": "HEAD | 200 | https://pgvjjtkkphjywusgfmnm.supabase.co/rest/v1/agendas?select=id | node",
    "headers": {},
    "regions": [],
    "log_type": "postgrest",
    "latency": 0,
    "log_count": null,
    "logs": [],
    "auth_user": null
  },
  {
    "id": "f4fa2cb1-fbf8-465d-9290-9b42618ab565",
    "date": "2026-06-30T05:02:23.484Z",
    "timestamp": "2026-06-30T05:02:23.484000",
    "level": "success",
    "status": "200",
    "method": "HEAD",
    "pathname": "/rest/v1/members",
    "event_message": "HEAD | 200 | https://pgvjjtkkphjywusgfmnm.supabase.co/rest/v1/members?select=id | node",
    "headers": {},
    "regions": [],
    "log_type": "postgrest",
    "latency": 0,
    "log_count": null,
    "logs": [],
    "auth_user": null
  },
  {
    "id": "9dfd058b-736e-4ed2-bfeb-5380c1c870e7",
    "date": "2026-06-30T05:02:23.483Z",
    "timestamp": "2026-06-30T05:02:23.483000",
    "level": "success",
    "status": "200",
    "method": "HEAD",
    "pathname": "/rest/v1/active_student_votes",
    "event_message": "HEAD | 200 | https://pgvjjtkkphjywusgfmnm.supabase.co/rest/v1/active_student_votes?select=id | node",
    "headers": {},
    "regions": [],
    "log_type": "postgrest",
    "latency": 0,
    "log_count": null,
    "logs": [],
    "auth_user": null
  },
  {
    "id": "ad7d8a8a-fe61-4ce2-9fd4-446d23749be8",
    "date": "2026-06-30T05:00:52.643Z",
    "timestamp": "2026-06-30T05:00:52.643484",
    "level": "success",
    "status": 200,
    "method": "",
    "pathname": "",
    "event_message": "Warp server error: Thread killed by timeout manager",
    "headers": {},
    "regions": [],
    "log_type": "postgrest",
    "latency": 0,
    "log_count": null,
    "logs": [],
    "auth_user": null
  }
]